README.txt
setup.py
collective/__init__.py
collective.geo.index.egg-info/PKG-INFO
collective.geo.index.egg-info/SOURCES.txt
collective.geo.index.egg-info/dependency_links.txt
collective.geo.index.egg-info/entry_points.txt
collective.geo.index.egg-info/namespace_packages.txt
collective.geo.index.egg-info/not-zip-safe
collective.geo.index.egg-info/requires.txt
collective.geo.index.egg-info/top_level.txt
collective/geo/__init__.py
collective/geo/index/__init__.py
collective/geo/index/configure.zcml
collective/geo/index/geometryindex.py
collective/geo/index/index.py
collective/geo/index/setuphandlers.py
collective/geo/index/tests.py
collective/geo/index/version.txt
collective/geo/index/browser/__init__.py
collective/geo/index/browser/configure.zcml
collective/geo/index/browser/kmlview.py
collective/geo/index/browser/maplayer.py
collective/geo/index/browser/query.py
collective/geo/index/browser/query_form.pt
collective/geo/index/browser/search.py
collective/geo/index/dtml/addGeometryIndex.dtml
collective/geo/index/dtml/browseGeometryIndex.dtml
collective/geo/index/dtml/manageGeometryIndex.dtml
collective/geo/index/profiles/default/collective.geo.index_various.txt
collective/geo/index/profiles/default/metadata.xml
collective/geo/index/www/index.gif
docs/HISTORY.txt
docs/INSTALL.txt
docs/LICENSE.GPL
docs/LICENSE.txt